aibaba_ai_community/__init__.py
aibaba_ai_community/adapters/__init__.py
aibaba_ai_community/adapters/openai.py
aibaba_ai_community/agent_toolkits/__init__.py
aibaba_ai_community/agent_toolkits/ainetwork/__init__.py
aibaba_ai_community/agent_toolkits/ainetwork/toolkit.py
aibaba_ai_community/agent_toolkits/amadeus/__init__.py
aibaba_ai_community/agent_toolkits/amadeus/toolkit.py
aibaba_ai_community/agent_toolkits/azure_ai_services.py
aibaba_ai_community/agent_toolkits/azure_cognitive_services.py
aibaba_ai_community/agent_toolkits/base.py
aibaba_ai_community/agent_toolkits/cassandra_database/__init__.py
aibaba_ai_community/agent_toolkits/cassandra_database/toolkit.py
aibaba_ai_community/agent_toolkits/clickup/__init__.py
aibaba_ai_community/agent_toolkits/clickup/toolkit.py
aibaba_ai_community/agent_toolkits/cogniswitch/__init__.py
aibaba_ai_community/agent_toolkits/cogniswitch/toolkit.py
aibaba_ai_community/agent_toolkits/connery/__init__.py
aibaba_ai_community/agent_toolkits/connery/toolkit.py
aibaba_ai_community/agent_toolkits/csv/__init__.py
aibaba_ai_community/agent_toolkits/file_management/__init__.py
aibaba_ai_community/agent_toolkits/file_management/toolkit.py
aibaba_ai_community/agent_toolkits/financial_datasets/__init__.py
aibaba_ai_community/agent_toolkits/financial_datasets/toolkit.py
aibaba_ai_community/agent_toolkits/github/__init__.py
aibaba_ai_community/agent_toolkits/github/toolkit.py
aibaba_ai_community/agent_toolkits/gitlab/__init__.py
aibaba_ai_community/agent_toolkits/gitlab/toolkit.py
aibaba_ai_community/agent_toolkits/gmail/__init__.py
aibaba_ai_community/agent_toolkits/gmail/toolkit.py
aibaba_ai_community/agent_toolkits/jira/__init__.py
aibaba_ai_community/agent_toolkits/jira/toolkit.py
aibaba_ai_community/agent_toolkits/json/__init__.py
aibaba_ai_community/agent_toolkits/json/base.py
aibaba_ai_community/agent_toolkits/json/prompt.py
aibaba_ai_community/agent_toolkits/json/toolkit.py
aibaba_ai_community/agent_toolkits/load_tools.py
aibaba_ai_community-0.3.15.dist-info/METADATA
aibaba_ai_community-0.3.15.dist-info/WHEEL
aibaba_ai_community-0.3.15.dist-info/RECORD
